pixeltools/__init__.py
pixeltools-0.0.0.0.dist-info/METADATA
pixeltools-0.0.0.0.dist-info/WHEEL
pixeltools-0.0.0.0.dist-info/entry_points.txt
pixeltools-0.0.0.0.dist-info/top_level.txt
pixeltools-0.0.0.0.dist-info/RECORD
