Metadata-Version: 2.1
Name: pixeltools
Version: 0.0.0.0
Summary: Pixel art manipulation tools
Home-page: https://github.com/doctorjei/pixeltools
Author: Jeremiah Blanchard
Author-email: jjb@eng.ufl.edu
License: GPL 3
Platform: UNKNOWN
